expy/LICENSE
expy/__init__.py
expy/colors.py
expy/extend.py
expy/inpoutx64.dll
expy/io.py
expy/readme.md
expy/recorder.py
expy/response.py
expy/scaffold.py
expy/shared.py
expy/simhei.ttf
expy/docs/api.md
expy/docs/api_template.txt
expy/docs/changelog.md
expy/docs/cookbook.md
expy/docs/cookbook_template.txt
expy/docs/docs_generator.py
expy/docs/index.md
expy/docs/keymap.md
expy/docs/quickstart.md
expy/docs/quickstart_template.txt
expy/docs/tip.md
expy/stim/display.py
expy/stim/draw.py
expy/stim/sound.py
expy/stim/video.py
expy/test/EXAMPLE -- Auditory Experiment.py
expy/test/EXAMPLE -- Priming Task.py
expy/test/EXAMPLE -- Visual Experiment.py
expy/test/bg.jpg
expy/test/io.py
expy/test/log.txt
expy/test/play_sound.py
expy/test/play_video.py
expy/test/preload.py
expy/test/read_setting.py
expy/test/response.py
expy/test/rsvp.py
expy/test/scaffold.py
expy/test/send_trigger.py
expy/test/setting.txt
expy/test/show_picture.py
expy/test/show_shape.py
expy/test/show_text.py
expy/test/sound_recording.py
expy/test/time_delay.1.py
expy/test/time_delay.2.py
expy/test/time_delay.py
expy/test/data/ba.wav
expy/test/data/da.wav
expy/test/data/demo.WAV
expy/test/data/demo.jpg
expy/test/data/demo.mpg
expy/test/data/poka.ogg
expy/test/data/pon.ogg
expy/test/data/record.wav
expy/test/data/trial_list.csv
expy/test/data/trial_list.xlsx
expy/test/data/trial_list2.csv
expy/test/result/_1_result.csv
expy/test/result/_2_result.csv
expy/test/result/_3_result.csv
expy/test/result/_result.csv
expy-0.9.14.dist-info/METADATA
expy-0.9.14.dist-info/RECORD
expy-0.9.14.dist-info/WHEEL
expy-0.9.14.dist-info/top_level.txt
