Metadata-Version: 2.1
Name: expy
Version: 0.9.14
Summary: A toolbox of psychological / neuroscience experiments
Home-page: UNKNOWN
Author: Jinbiao Yang
Author-email: ray306@gmail.com
License: GPL License
Requires-Dist: numpy
Requires-Dist: pandas
Requires-Dist: scipy
Requires-Dist: pyglet
Requires-Dist: librosa
Requires-Dist: pyaudio
Requires-Dist: pyserial
